jinx/__init__.py
jinx/errors.py
jinx/primitives.py
jinx/shell.py
jinx/vocabulary.py
jinx/word_evaluation.py
jinx/word_formation.py
jinx/word_spelling.py
jinx/execution/executor.py
jinx/execution/jax/__init__.py
jinx/execution/jax/adverbs.py
jinx/execution/jax/application.py
jinx/execution/jax/verbs.py
jinx/execution/numpy/__init__.py
jinx/execution/numpy/adverbs.py
jinx/execution/numpy/application.py
jinx/execution/numpy/conjunctions.py
jinx/execution/numpy/conversion.py
jinx/execution/numpy/helpers.py
jinx/execution/numpy/printing.py
jinx/execution/numpy/verbs.py
jjinx-0.0.1.dist-info/licenses/LICENSE
jjinx-0.0.1.dist-info/METADATA
jjinx-0.0.1.dist-info/WHEEL
jjinx-0.0.1.dist-info/entry_points.txt
jjinx-0.0.1.dist-info/top_level.txt
jjinx-0.0.1.dist-info/RECORD
