Metadata-Version: 2.4
Name: jjinx
Version: 0.0.1
Summary: Interpreter for the J programming language.
Author: Alex Riley
License: MIT License
Project-URL: Homepage, https://github.com/ajcr/jinx
Keywords: J,interpreter
Classifier: Development Status :: 3 - Alpha
Classifier: Topic :: Scientific/Engineering :: Mathematics
Classifier: Topic :: Utilities
Classifier: Typing :: Typed
Classifier: Intended Audience :: Science/Research
Classifier: License :: OSI Approved :: MIT License
Classifier: Programming Language :: Python :: 3.13
Requires-Python: >=3.13
License-File: LICENSE
Requires-Dist: numpy>=2.3.3
Dynamic: license-file
